ez_rq/__init__.py
ez_rq/aiohttp_wrap.py
ez_rq/util.py
ez_aiohttp-0.1.0.dist-info/METADATA
ez_aiohttp-0.1.0.dist-info/WHEEL
ez_aiohttp-0.1.0.dist-info/top_level.txt
ez_aiohttp-0.1.0.dist-info/RECORD
