Metadata-Version: 2.1
Name: ez-aiohttp
Version: 0.1.0
Summary: Make aiohttp easier
Home-page: https://ez-aiohttp.rukchadisa.live/en/latest/
Author: Rukchad Wongprayoon
Author-email: contact@biomooping.tk
License: UNKNOWN
Platform: UNKNOWN
Requires-Dist: aiohttp[speedups]
Requires-Dist: dta
